tslumen/__init__.py
tslumen/_version.py
tslumen/jinja_utils.py
tslumen/misc.py
tslumen/py.typed
tslumen/scheduling.py
tslumen/cli/__init__.py
tslumen/cli/readers.py
tslumen/plot/__init__.py
tslumen/plot/utils.py
tslumen/plot/interactive/__init__.py
tslumen/plot/interactive/base.py
tslumen/plot/interactive/comparison.py
tslumen/plot/interactive/correlation.py
tslumen/plot/interactive/distribution.py
tslumen/plot/interactive/line.py
tslumen/plot/interactive/misc.py
tslumen/plot/static/__init__.py
tslumen/plot/static/base.py
tslumen/plot/static/comparison.py
tslumen/plot/static/correlation.py
tslumen/plot/static/distribution.py
tslumen/plot/static/line.py
tslumen/plot/static/misc.py
tslumen/profile/__init__.py
tslumen/profile/_supsmu.py
tslumen/profile/base.py
tslumen/profile/components.py
tslumen/profile/correlation.py
tslumen/profile/distribution.py
tslumen/profile/features.py
tslumen/profile/smooth.py
tslumen/profile/stat_tests.py
tslumen/profile/stats.py
tslumen/profile/summary.py
tslumen/report/__init__.py
tslumen/report/base.py
tslumen/report/dashboard/__init__.py
tslumen/report/dashboard/_dash.py
tslumen/report/dashboard/base.py
tslumen/report/dashboard/report.py
tslumen/report/dashboard/sections/__init__.py
tslumen/report/dashboard/sections/features.py
tslumen/report/dashboard/sections/relations.py
tslumen/report/dashboard/sections/summary.py
tslumen/report/dashboard/sections/timeseries.py
tslumen/report/html/__init__.py
tslumen/report/html/base.py
tslumen/report/html/report.py
tslumen/report/html/sections.py
tslumen/templates/dashboard/index.html
tslumen/templates/dashboard/static/bootstrap-icons.css
tslumen/templates/dashboard/static/bootstrap.bundle.min.js
tslumen/templates/dashboard/static/bootstrap.min.css
tslumen/templates/dashboard/static/favicon.png
tslumen/templates/dashboard/static/jquery-3.5.1.min.js
tslumen/templates/dashboard/static/logo.svg
tslumen/templates/dashboard/static/sboot.css
tslumen/templates/dashboard/static/script.js
tslumen-0.0.1.dist-info/LICENSE
tslumen-0.0.1.dist-info/METADATA
tslumen-0.0.1.dist-info/WHEEL
tslumen-0.0.1.dist-info/entry_points.txt
tslumen-0.0.1.dist-info/top_level.txt
tslumen-0.0.1.dist-info/RECORD
