Metadata-Version: 2.1
Name: tslumen
Version: 0.0.1
Summary: A library for Time Series exploratory data analysis
Home-page: https://github.com/hsbc/tslumen
Author: HSBC
Author-email: opensource@hsbc.com
License: Apache Software License
Project-URL: Homepage, https://hsbc.github.io/tslumen
Project-URL: Repository, https://github.com/hsbc/tslumen
Project-URL: BugTracker, https://github.com/hsbc/tslumen/issues
Project-URL: Documentation, https://hsbc.github.io/tslumen/html
Project-URL: Changelog, https://github.com/hsbc/tslumen/blob/main/CHANGELOG.md
Keywords: timeseries,time-series,profiling,exploratory-data-analysis,time-series-analysis,forecasting,data-science,machine-learning,data-mining,jupyter
Platform: UNKNOWN
Classifier: Development Status :: 4 - Beta
Classifier: Intended Audience :: Developers
Classifier: Intended Audience :: Financial and Insurance Industry
Classifier: Intended Audience :: Healthcare Industry
Classifier: Intended Audience :: Science/Research
Classifier: License :: OSI Approved :: Apache Software License
Classifier: Natural Language :: English
Classifier: Operating System :: MacOS
Classifier: Operating System :: Microsoft :: Windows
Classifier: Operating System :: OS Independent
Classifier: Operating System :: POSIX
Classifier: Operating System :: Unix
Classifier: Programming Language :: Python
Classifier: Programming Language :: Python :: 3
Classifier: Programming Language :: Python :: 3.6
Classifier: Programming Language :: Python :: 3.7
Classifier: Programming Language :: Python :: 3.8
Classifier: Programming Language :: Python :: 3.9
Classifier: Programming Language :: Python :: 3.10
Classifier: Topic :: Office/Business :: Financial
Classifier: Topic :: Scientific/Engineering
Classifier: Topic :: Scientific/Engineering :: Artificial Intelligence
Classifier: Topic :: Scientific/Engineering :: Information Analysis
Classifier: Topic :: Scientific/Engineering :: Visualization
Classifier: Typing :: Typed
Requires-Python: >=3.6.0
License-File: LICENSE
Requires-Dist: hydra-core (<2.0,>=1.1)
Requires-Dist: hydra-colorlog
Requires-Dist: typing-inspect (>=0.6.0)
Requires-Dist: numpy (>=1.19)
Requires-Dist: pandas (!=1.4.0,<1.5.0,>=1.0.0)
Requires-Dist: jinja2 (<3.1,>=3.0)
Requires-Dist: matplotlib (<4.0.0,>=3.3.2)
Requires-Dist: networkx
Requires-Dist: scipy (>=1.5.0)
Requires-Dist: statsmodels (<0.14,>=0.12.0)
Requires-Dist: supersmoother (==0.4)
Requires-Dist: joblib (>=1.0.0<2.0.0)
Requires-Dist: tqdm
Requires-Dist: PyYAML (>=5.0.0)
Provides-Extra: extras
Requires-Dist: plotly (<6.0.0,>=4.12.0) ; extra == 'extras'
Requires-Dist: jupyter-dash (<0.5,>=0.3) ; extra == 'extras'
Requires-Dist: dash (<2.7,>=1.20) ; extra == 'extras'
Requires-Dist: dash-bootstrap-components (>1.0.0) ; extra == 'extras'
